easy_webhook/__init__.py
easy_webhook/webhook.py
easy_webhook-0.0.1.dist-info/LICENSE
easy_webhook-0.0.1.dist-info/METADATA
easy_webhook-0.0.1.dist-info/WHEEL
easy_webhook-0.0.1.dist-info/top_level.txt
easy_webhook-0.0.1.dist-info/RECORD
