Metadata-Version: 2.1
Name: easy-webhook
Version: 0.0.1
Summary: easy discord webhook wrapper
Author: SmurkMica
Author-email: author@example.com
Classifier: Programming Language :: Python :: 3
Classifier: License :: OSI Approved :: MIT License
Classifier: Operating System :: OS Independent
License-File: LICENSE
